{
  "files": [
    {
      "path": "./dist/css/bootstrap-grid.css",
      "maxSize": "9.5 kB"
    },
    {
      "path": "./dist/css/bootstrap-grid.min.css",
      "maxSize": "8.5 kB"
    },
    {
      "path": "./dist/css/bootstrap-reboot.css",
      "maxSize": "5.25 kB"
    },
    {
      "path": "./dist/css/bootstrap-reboot.min.css",
      "maxSize": "4.25 kB"
    },
    {
      "path": "./dist/css/bootstrap-utilities.css",
      "maxSize": "14.5 kB"
    },
    {
      "path": "./dist/css/bootstrap-utilities.min.css",
      "maxSize": "12.75 kB"
    },
    {
      "path": "./dist/css/bootstrap.css",
      "maxSize": "36.0 kB"
    },
    {
      "path": "./dist/css/bootstrap.min.css",
      "maxSize": "32.5 kB"
    },
    {
      "path": "./dist/js/bootstrap.bundle.js",
      "maxSize": "49.75 kB"
    },
    {
      "path": "./dist/js/bootstrap.bundle.min.js",
      "maxSize": "26.0 kB"
    },
    {
      "path": "./dist/js/bootstrap.esm.js",
      "maxSize": "36.0 kB"
    },
    {
      "path": "./dist/js/bootstrap.esm.min.js",
      "maxSize": "22.25 kB"
    },
    {
      "path": "./dist/js/bootstrap.js",
      "maxSize": "36.5 kB"
    },
    {
      "path": "./dist/js/bootstrap.min.js",
      "maxSize": "19.75 kB"
    }
  ],
  "ci": {
    "trackBranches": [
      "main",
      "v4-dev"
    ]
  }
}
